[
	{
		"id": 1,
		"vehiculo": {
			"tipo": "Camion",
			"numeroMotor": 8918,
			"numeroRuedas": 6,
			"tipoCombustible": "Gasolina",
			"maxLitros": 228,
			"marca": "MAN",
			"precio": 105000000,
			"anio": 2009,
			"numeroPuertas": 3
		},
		"cliente": {
			"nombre": "Pedro",
			"rut": "22222222-2"
		}
	},
	{
		"id": 2,
		"vehiculo": {
			"tipo": "Camion",
			"numeroMotor": 9997,
			"numeroRuedas": 7,
			"tipoCombustible": "Gas",
			"maxLitros": 243,
			"marca": "Iveco",
			"precio": 85000000,
			"anio": 2007,
			"numeroPuertas": 2
		},
		"cliente": {
			"nombre": "Maria",
			"rut": "33333333-3"
		}
	},
	{
		"id": 3,
		"vehiculo": {
			"tipo": "Camion",
			"numeroMotor": 7092,
			"numeroRuedas": 15,
			"tipoCombustible": "Electrico",
			"maxLitros": 400,
			"marca": "Mercedes",
			"precio": 110000000,
			"anio": 2007,
			"numeroPuertas": 2
		},
		"cliente": {
			"nombre": "Pedro",
			"rut": "22222222-2"
		}
	},
	{
		"id": 4,
		"vehiculo": {
			"tipo": "Auto",
			"numeroMotor": 2569,
			"numeroRuedas": 4,
			"tipoCombustible": "Electrico",
			"maxLitros": 46,
			"marca": "Chevrolet",
			"precio": 18000000,
			"anio": 1991,
			"numeroPuertas": 2
		},
		"cliente": {
			"nombre": "Carlos",
			"rut": "55555555-5"
		}
	},
	{
		"id": 5,
		"vehiculo": {
			"tipo": "Moto",
			"numeroMotor": 1233,
			"numeroRuedas": 2,
			"tipoCombustible": "Gasolina",
			"maxLitros": 22,
			"marca": "BMW",
			"precio": 18000000,
			"anio": 1987
		},
		"cliente": {
			"nombre": "Carlos",
			"rut": "55555555-5"
		}
	},
	{
		"id": 6,
		"vehiculo": {
			"tipo": "Moto",
			"numeroMotor": 1171,
			"numeroRuedas": 2,
			"tipoCombustible": "Electrico",
			"maxLitros": 20,
			"marca": "Kawasaki",
			"precio": 13000000,
			"anio": 2018
		},
		"cliente": {
			"nombre": "Carlos",
			"rut": "55555555-5"
		}
	},
	{
		"id": 7,
		"vehiculo": {
			"tipo": "Moto",
			"numeroMotor": 6293,
			"numeroRuedas": 2,
			"tipoCombustible": "Electrico",
			"maxLitros": 28,
			"marca": "Honda",
			"precio": 15000000,
			"anio": 1982
		},
		"cliente": {
			"nombre": "Carlos",
			"rut": "55555555-5"
		}
	},
	{
		"id": 8,
		"vehiculo": {
			"tipo": "Camion",
			"numeroMotor": 7105,
			"numeroRuedas": 18,
			"tipoCombustible": "Electrico",
			"maxLitros": 212,
			"marca": "Scania",
			"precio": 95000000,
			"anio": 1999,
			"numeroPuertas": 2
		},
		"cliente": {
			"nombre": "Maria",
			"rut": "33333333-3"
		}
	},
	{
		"id": 9,
		"vehiculo": {
			"tipo": "Moto",
			"numeroMotor": 2284,
			"numeroRuedas": 2,
			"tipoCombustible": "Electrico",
			"maxLitros": 13,
			"marca": "Honda",
			"precio": 15000000,
			"anio": 1993
		},
		"cliente": {
			"nombre": "Juan",
			"rut": "11111111-1"
		}
	},
	{
		"id": 10,
		"vehiculo": {
			"tipo": "Moto",
			"numeroMotor": 2875,
			"numeroRuedas": 2,
			"tipoCombustible": "Gasolina",
			"maxLitros": 20,
			"marca": "Honda",
			"precio": 15000000,
			"anio": 1991
		},
		"cliente": {
			"nombre": "Carlos",
			"rut": "55555555-5"
		}
	},
	{
		"id": 11,
		"vehiculo": {
			"tipo": "Moto",
			"numeroMotor": 7756,
			"numeroRuedas": 2,
			"tipoCombustible": "Electrico",
			"maxLitros": 26,
			"marca": "KTM",
			"precio": 5000000,
			"anio": 2004
		},
		"cliente": {
			"nombre": "Juan",
			"rut": "11111111-1"
		}
	},
	{
		"id": 12,
		"vehiculo": {
			"tipo": "Auto",
			"numeroMotor": 9608,
			"numeroRuedas": 4,
			"tipoCombustible": "Gasolina",
			"maxLitros": 42,
			"marca": "Suzuki",
			"precio": 12000000,
			"anio": 2011,
			"numeroPuertas": 2
		},
		"cliente": {
			"nombre": "Luis",
			"rut": "77777777-7"
		}
	},
	{
		"id": 13,
		"vehiculo": {
			"tipo": "Moto",
			"numeroMotor": 5691,
			"numeroRuedas": 2,
			"tipoCombustible": "Electrico",
			"maxLitros": 18,
			"marca": "Suzuki",
			"precio": 8000000,
			"anio": 2017
		},
		"cliente": {
			"nombre": "Ana",
			"rut": "44444444-4"
		}
	},
	{
		"id": 14,
		"vehiculo": {
			"tipo": "Moto",
			"numeroMotor": 4908,
			"numeroRuedas": 2,
			"tipoCombustible": "Gasolina",
			"maxLitros": 21,
			"marca": "KTM",
			"precio": 5000000,
			"anio": 1986
		},
		"cliente": {
			"nombre": "Pedro",
			"rut": "22222222-2"
		}
	},
	{
		"id": 15,
		"vehiculo": {
			"tipo": "Camion",
			"numeroMotor": 5298,
			"numeroRuedas": 7,
			"tipoCombustible": "Electrico",
			"maxLitros": 209,
			"marca": "Scania",
			"precio": 95000000,
			"anio": 2012,
			"numeroPuertas": 2
		},
		"cliente": {
			"nombre": "Ana",
			"rut": "44444444-4"
		}
	},
	{
		"id": 16,
		"vehiculo": {
			"tipo": "Camion",
			"numeroMotor": 6719,
			"numeroRuedas": 4,
			"tipoCombustible": "Gas",
			"maxLitros": 236,
			"marca": "Volvo",
			"precio": 100000000,
			"anio": 2021,
			"numeroPuertas": 2
		},
		"cliente": {
			"nombre": "Luis",
			"rut": "77777777-7"
		}
	},
	{
		"id": 17,
		"vehiculo": {
			"tipo": "Camion",
			"numeroMotor": 1446,
			"numeroRuedas": 14,
			"tipoCombustible": "Electrico",
			"maxLitros": 448,
			"marca": "Isuzu",
			"precio": 70000000,
			"anio": 2022,
			"numeroPuertas": 3
		},
		"cliente": {
			"nombre": "Sofia",
			"rut": "66666666-6"
		}
	},
	{
		"id": 18,
		"vehiculo": {
			"tipo": "Moto",
			"numeroMotor": 9741,
			"numeroRuedas": 2,
			"tipoCombustible": "Gas",
			"maxLitros": 25,
			"marca": "KTM",
			"precio": 5000000,
			"anio": 1982
		},
		"cliente": {
			"nombre": "Carlos",
			"rut": "55555555-5"
		}
	},
	{
		"id": 19,
		"vehiculo": {
			"tipo": "Auto",
			"numeroMotor": 7534,
			"numeroRuedas": 4,
			"tipoCombustible": "Gasolina",
			"maxLitros": 54,
			"marca": "Suzuki",
			"precio": 12000000,
			"anio": 2010,
			"numeroPuertas": 4
		},
		"cliente": {
			"nombre": "Ana",
			"rut": "44444444-4"
		}
	},
	{
		"id": 20,
		"vehiculo": {
			"tipo": "Auto",
			"numeroMotor": 7691,
			"numeroRuedas": 4,
			"tipoCombustible": "Gasolina",
			"maxLitros": 58,
			"marca": "Suzuki",
			"precio": 12000000,
			"anio": 2013,
			"numeroPuertas": 3
		},
		"cliente": {
			"nombre": "Luis",
			"rut": "77777777-7"
		}
	},
	{
		"id": 21,
		"vehiculo": {
			"tipo": "Moto",
			"numeroMotor": 8606,
			"numeroRuedas": 2,
			"tipoCombustible": "Gasolina",
			"maxLitros": 13,
			"marca": "BMW",
			"precio": 18000000,
			"anio": 2000
		},
		"cliente": {
			"nombre": "Juan",
			"rut": "11111111-1"
		}
	},
	{
		"id": 22,
		"vehiculo": {
			"tipo": "Auto",
			"numeroMotor": 8655,
			"numeroRuedas": 4,
			"tipoCombustible": "Gas",
			"maxLitros": 67,
			"marca": "Honda",
			"precio": 21000000,
			"anio": 1998,
			"numeroPuertas": 2
		},
		"cliente": {
			"nombre": "Sofia",
			"rut": "66666666-6"
		}
	},
	{
		"id": 23,
		"vehiculo": {
			"tipo": "Auto",
			"numeroMotor": 9677,
			"numeroRuedas": 4,
			"tipoCombustible": "Gasolina",
			"maxLitros": 40,
			"marca": "Ford",
			"precio": 17000000,
			"anio": 1989,
			"numeroPuertas": 2
		},
		"cliente": {
			"nombre": "Pedro",
			"rut": "22222222-2"
		}
	},
	{
		"id": 24,
		"vehiculo": {
			"tipo": "Auto",
			"numeroMotor": 8871,
			"numeroRuedas": 4,
			"tipoCombustible": "Gas",
			"maxLitros": 57,
			"marca": "Honda",
			"precio": 21000000,
			"anio": 1980,
			"numeroPuertas": 5
		},
		"cliente": {
			"nombre": "Maria",
			"rut": "33333333-3"
		}
	},
	{
		"id": 25,
		"vehiculo": {
			"tipo": "Moto",
			"numeroMotor": 9352,
			"numeroRuedas": 2,
			"tipoCombustible": "Gas",
			"maxLitros": 27,
			"marca": "Suzuki",
			"precio": 8000000,
			"anio": 2019
		},
		"cliente": {
			"nombre": "Juan",
			"rut": "11111111-1"
		}
	},
	{
		"id": 26,
		"vehiculo": {
			"tipo": "Camion",
			"numeroMotor": 2358,
			"numeroRuedas": 14,
			"tipoCombustible": "Gasolina",
			"maxLitros": 295,
			"marca": "Iveco",
			"precio": 85000000,
			"anio": 2011,
			"numeroPuertas": 2
		},
		"cliente": {
			"nombre": "Sofia",
			"rut": "66666666-6"
		}
	},
	{
		"id": 27,
		"vehiculo": {
			"tipo": "Camion",
			"numeroMotor": 9467,
			"numeroRuedas": 12,
			"tipoCombustible": "Gasolina",
			"maxLitros": 466,
			"marca": "Mercedes",
			"precio": 110000000,
			"anio": 2019,
			"numeroPuertas": 3
		},
		"cliente": {
			"nombre": "Luis",
			"rut": "77777777-7"
		}
	},
	{
		"id": 28,
		"vehiculo": {
			"tipo": "Camion",
			"numeroMotor": 9310,
			"numeroRuedas": 4,
			"tipoCombustible": "Gas",
			"maxLitros": 447,
			"marca": "Isuzu",
			"precio": 70000000,
			"anio": 1990,
			"numeroPuertas": 2
		},
		"cliente": {
			"nombre": "Juan",
			"rut": "11111111-1"
		}
	},
	{
		"id": 29,
		"vehiculo": {
			"tipo": "Moto",
			"numeroMotor": 5528,
			"numeroRuedas": 2,
			"tipoCombustible": "Gas",
			"maxLitros": 20,
			"marca": "Honda",
			"precio": 15000000,
			"anio": 2015
		},
		"cliente": {
			"nombre": "Carlos",
			"rut": "55555555-5"
		}
	},
	{
		"id": 30,
		"vehiculo": {
			"tipo": "Camion",
			"numeroMotor": 1881,
			"numeroRuedas": 17,
			"tipoCombustible": "Electrico",
			"maxLitros": 299,
			"marca": "Scania",
			"precio": 95000000,
			"anio": 2000,
			"numeroPuertas": 3
		},
		"cliente": {
			"nombre": "Maria",
			"rut": "33333333-3"
		}
	},
	{
		"id": 31,
		"vehiculo": {
			"tipo": "Moto",
			"numeroMotor": 4964,
			"numeroRuedas": 2,
			"tipoCombustible": "Gasolina",
			"maxLitros": 16,
			"marca": "Kawasaki",
			"precio": 13000000,
			"anio": 1998
		},
		"cliente": {
			"nombre": "Maria",
			"rut": "33333333-3"
		}
	},
	{
		"id": 32,
		"vehiculo": {
			"tipo": "Moto",
			"numeroMotor": 3699,
			"numeroRuedas": 2,
			"tipoCombustible": "Gas",
			"maxLitros": 25,
			"marca": "KTM",
			"precio": 5000000,
			"anio": 1982
		},
		"cliente": {
			"nombre": "Luis",
			"rut": "77777777-7"
		}
	},
	{
		"id": 33,
		"vehiculo": {
			"tipo": "Auto",
			"numeroMotor": 9427,
			"numeroRuedas": 4,
			"tipoCombustible": "Electrico",
			"maxLitros": 69,
			"marca": "Chevrolet",
			"precio": 18000000,
			"anio": 2009,
			"numeroPuertas": 2
		},
		"cliente": {
			"nombre": "Luis",
			"rut": "77777777-7"
		}
	},
	{
		"id": 34,
		"vehiculo": {
			"tipo": "Moto",
			"numeroMotor": 5536,
			"numeroRuedas": 2,
			"tipoCombustible": "Electrico",
			"maxLitros": 26,
			"marca": "BMW",
			"precio": 18000000,
			"anio": 1985
		},
		"cliente": {
			"nombre": "Pedro",
			"rut": "22222222-2"
		}
	},
	{
		"id": 35,
		"vehiculo": {
			"tipo": "Moto",
			"numeroMotor": 3392,
			"numeroRuedas": 2,
			"tipoCombustible": "Gas",
			"maxLitros": 15,
			"marca": "Honda",
			"precio": 15000000,
			"anio": 1985
		},
		"cliente": {
			"nombre": "Juan",
			"rut": "11111111-1"
		}
	},
	{
		"id": 36,
		"vehiculo": {
			"tipo": "Auto",
			"numeroMotor": 4614,
			"numeroRuedas": 4,
			"tipoCombustible": "Electrico",
			"maxLitros": 62,
			"marca": "Hyundai",
			"precio": 16000000,
			"anio": 2006,
			"numeroPuertas": 3
		},
		"cliente": {
			"nombre": "Ana",
			"rut": "44444444-4"
		}
	},
	{
		"id": 37,
		"vehiculo": {
			"tipo": "Auto",
			"numeroMotor": 6468,
			"numeroRuedas": 4,
			"tipoCombustible": "Gasolina",
			"maxLitros": 46,
			"marca": "Chevrolet",
			"precio": 18000000,
			"anio": 2019,
			"numeroPuertas": 3
		},
		"cliente": {
			"nombre": "Ana",
			"rut": "44444444-4"
		}
	},
	{
		"id": 38,
		"vehiculo": {
			"tipo": "Auto",
			"numeroMotor": 5642,
			"numeroRuedas": 4,
			"tipoCombustible": "Gasolina",
			"maxLitros": 50,
			"marca": "Chevrolet",
			"precio": 18000000,
			"anio": 1983,
			"numeroPuertas": 5
		},
		"cliente": {
			"nombre": "Maria",
			"rut": "33333333-3"
		}
	},
	{
		"id": 39,
		"vehiculo": {
			"tipo": "Moto",
			"numeroMotor": 5267,
			"numeroRuedas": 2,
			"tipoCombustible": "Gas",
			"maxLitros": 24,
			"marca": "BMW",
			"precio": 18000000,
			"anio": 1999
		},
		"cliente": {
			"nombre": "Juan",
			"rut": "11111111-1"
		}
	},
	{
		"id": 40,
		"vehiculo": {
			"tipo": "Camion",
			"numeroMotor": 6772,
			"numeroRuedas": 7,
			"tipoCombustible": "Electrico",
			"maxLitros": 372,
			"marca": "MAN",
			"precio": 105000000,
			"anio": 1980,
			"numeroPuertas": 3
		},
		"cliente": {
			"nombre": "Pedro",
			"rut": "22222222-2"
		}
	},
	{
		"id": 41,
		"vehiculo": {
			"tipo": "Moto",
			"numeroMotor": 9921,
			"numeroRuedas": 2,
			"tipoCombustible": "Gasolina",
			"maxLitros": 18,
			"marca": "Kawasaki",
			"precio": 13000000,
			"anio": 2007
		},
		"cliente": {
			"nombre": "Luis",
			"rut": "77777777-7"
		}
	},
	{
		"id": 42,
		"vehiculo": {
			"tipo": "Camion",
			"numeroMotor": 3706,
			"numeroRuedas": 4,
			"tipoCombustible": "Electrico",
			"maxLitros": 275,
			"marca": "Volvo",
			"precio": 100000000,
			"anio": 1993,
			"numeroPuertas": 3
		},
		"cliente": {
			"nombre": "Carlos",
			"rut": "55555555-5"
		}
	},
	{
		"id": 43,
		"vehiculo": {
			"tipo": "Auto",
			"numeroMotor": 2805,
			"numeroRuedas": 4,
			"tipoCombustible": "Gas",
			"maxLitros": 63,
			"marca": "Ford",
			"precio": 17000000,
			"anio": 1997,
			"numeroPuertas": 5
		},
		"cliente": {
			"nombre": "Juan",
			"rut": "11111111-1"
		}
	},
	{
		"id": 44,
		"vehiculo": {
			"tipo": "Moto",
			"numeroMotor": 9954,
			"numeroRuedas": 2,
			"tipoCombustible": "Gasolina",
			"maxLitros": 20,
			"marca": "BMW",
			"precio": 18000000,
			"anio": 1989
		},
		"cliente": {
			"nombre": "Juan",
			"rut": "11111111-1"
		}
	},
	{
		"id": 45,
		"vehiculo": {
			"tipo": "Auto",
			"numeroMotor": 2960,
			"numeroRuedas": 4,
			"tipoCombustible": "Gas",
			"maxLitros": 46,
			"marca": "Chevrolet",
			"precio": 18000000,
			"anio": 1995,
			"numeroPuertas": 2
		},
		"cliente": {
			"nombre": "Luis",
			"rut": "77777777-7"
		}
	},
	{
		"id": 46,
		"vehiculo": {
			"tipo": "Camion",
			"numeroMotor": 6050,
			"numeroRuedas": 4,
			"tipoCombustible": "Gasolina",
			"maxLitros": 434,
			"marca": "Scania",
			"precio": 95000000,
			"anio": 2002,
			"numeroPuertas": 2
		},
		"cliente": {
			"nombre": "Pedro",
			"rut": "22222222-2"
		}
	},
	{
		"id": 47,
		"vehiculo": {
			"tipo": "Auto",
			"numeroMotor": 9408,
			"numeroRuedas": 4,
			"tipoCombustible": "Electrico",
			"maxLitros": 54,
			"marca": "Suzuki",
			"precio": 12000000,
			"anio": 2000,
			"numeroPuertas": 4
		},
		"cliente": {
			"nombre": "Carlos",
			"rut": "55555555-5"
		}
	},
	{
		"id": 48,
		"vehiculo": {
			"tipo": "Moto",
			"numeroMotor": 4509,
			"numeroRuedas": 2,
			"tipoCombustible": "Gasolina",
			"maxLitros": 29,
			"marca": "KTM",
			"precio": 5000000,
			"anio": 2017
		},
		"cliente": {
			"nombre": "Luis",
			"rut": "77777777-7"
		}
	},
	{
		"id": 49,
		"vehiculo": {
			"tipo": "Moto",
			"numeroMotor": 7757,
			"numeroRuedas": 2,
			"tipoCombustible": "Gas",
			"maxLitros": 11,
			"marca": "Suzuki",
			"precio": 8000000,
			"anio": 2003
		},
		"cliente": {
			"nombre": "Carlos",
			"rut": "55555555-5"
		}
	},
	{
		"id": 50,
		"vehiculo": {
			"tipo": "Camion",
			"numeroMotor": 9605,
			"numeroRuedas": 4,
			"tipoCombustible": "Gas",
			"maxLitros": 468,
			"marca": "Iveco",
			"precio": 85000000,
			"anio": 1998,
			"numeroPuertas": 2
		},
		"cliente": {
			"nombre": "Juan",
			"rut": "11111111-1"
		}
	},
	{
		"id": 51,
		"vehiculo": {
			"tipo": "Auto",
			"numeroMotor": 5898,
			"numeroRuedas": 4,
			"tipoCombustible": "Electrico",
			"maxLitros": 47,
			"marca": "Honda",
			"precio": 21000000,
			"anio": 2017,
			"numeroPuertas": 3
		},
		"cliente": {
			"nombre": "Maria",
			"rut": "33333333-3"
		}
	},
	{
		"id": 52,
		"vehiculo": {
			"tipo": "Auto",
			"numeroMotor": 2695,
			"numeroRuedas": 4,
			"tipoCombustible": "Electrico",
			"maxLitros": 48,
			"marca": "Suzuki",
			"precio": 12000000,
			"anio": 1993,
			"numeroPuertas": 4
		},
		"cliente": {
			"nombre": "Pedro",
			"rut": "22222222-2"
		}
	},
	{
		"id": 53,
		"vehiculo": {
			"tipo": "Camion",
			"numeroMotor": 9298,
			"numeroRuedas": 14,
			"tipoCombustible": "Gasolina",
			"maxLitros": 477,
			"marca": "Mercedes",
			"precio": 110000000,
			"anio": 2021,
			"numeroPuertas": 2
		},
		"cliente": {
			"nombre": "Juan",
			"rut": "11111111-1"
		}
	},
	{
		"id": 54,
		"vehiculo": {
			"tipo": "Auto",
			"numeroMotor": 5523,
			"numeroRuedas": 4,
			"tipoCombustible": "Gas",
			"maxLitros": 52,
			"marca": "Chevrolet",
			"precio": 18000000,
			"anio": 2002,
			"numeroPuertas": 2
		},
		"cliente": {
			"nombre": "Luis",
			"rut": "77777777-7"
		}
	},
	{
		"id": 55,
		"vehiculo": {
			"tipo": "Camion",
			"numeroMotor": 7497,
			"numeroRuedas": 4,
			"tipoCombustible": "Gasolina",
			"maxLitros": 488,
			"marca": "Mercedes",
			"precio": 110000000,
			"anio": 2011,
			"numeroPuertas": 2
		},
		"cliente": {
			"nombre": "Sofia",
			"rut": "66666666-6"
		}
	},
	{
		"id": 56,
		"vehiculo": {
			"tipo": "Camion",
			"numeroMotor": 4638,
			"numeroRuedas": 9,
			"tipoCombustible": "Gas",
			"maxLitros": 410,
			"marca": "MAN",
			"precio": 105000000,
			"anio": 2002,
			"numeroPuertas": 2
		},
		"cliente": {
			"nombre": "Ana",
			"rut": "44444444-4"
		}
	},
	{
		"id": 57,
		"vehiculo": {
			"tipo": "Auto",
			"numeroMotor": 4523,
			"numeroRuedas": 4,
			"tipoCombustible": "Electrico",
			"maxLitros": 55,
			"marca": "Hyundai",
			"precio": 16000000,
			"anio": 2016,
			"numeroPuertas": 5
		},
		"cliente": {
			"nombre": "Pedro",
			"rut": "22222222-2"
		}
	},
	{
		"id": 58,
		"vehiculo": {
			"tipo": "Camion",
			"numeroMotor": 7153,
			"numeroRuedas": 15,
			"tipoCombustible": "Gas",
			"maxLitros": 448,
			"marca": "Volvo",
			"precio": 100000000,
			"anio": 2006,
			"numeroPuertas": 3
		},
		"cliente": {
			"nombre": "Ana",
			"rut": "44444444-4"
		}
	},
	{
		"id": 59,
		"vehiculo": {
			"tipo": "Auto",
			"numeroMotor": 2854,
			"numeroRuedas": 4,
			"tipoCombustible": "Gasolina",
			"maxLitros": 65,
			"marca": "Suzuki",
			"precio": 12000000,
			"anio": 2021,
			"numeroPuertas": 3
		},
		"cliente": {
			"nombre": "Carlos",
			"rut": "55555555-5"
		}
	},
	{
		"id": 60,
		"vehiculo": {
			"tipo": "Moto",
			"numeroMotor": 3919,
			"numeroRuedas": 2,
			"tipoCombustible": "Gas",
			"maxLitros": 24,
			"marca": "KTM",
			"precio": 5000000,
			"anio": 1993
		},
		"cliente": {
			"nombre": "Pedro",
			"rut": "22222222-2"
		}
	},
	{
		"id": 61,
		"vehiculo": {
			"tipo": "Moto",
			"numeroMotor": 8090,
			"numeroRuedas": 2,
			"tipoCombustible": "Electrico",
			"maxLitros": 10,
			"marca": "BMW",
			"precio": 18000000,
			"anio": 1988
		},
		"cliente": {
			"nombre": "Sofia",
			"rut": "66666666-6"
		}
	},
	{
		"id": 62,
		"vehiculo": {
			"tipo": "Moto",
			"numeroMotor": 8526,
			"numeroRuedas": 2,
			"tipoCombustible": "Gas",
			"maxLitros": 10,
			"marca": "Kawasaki",
			"precio": 13000000,
			"anio": 2002
		},
		"cliente": {
			"nombre": "Juan",
			"rut": "11111111-1"
		}
	},
	{
		"id": 63,
		"vehiculo": {
			"tipo": "Moto",
			"numeroMotor": 2746,
			"numeroRuedas": 2,
			"tipoCombustible": "Gas",
			"maxLitros": 10,
			"marca": "BMW",
			"precio": 18000000,
			"anio": 1985
		},
		"cliente": {
			"nombre": "Pedro",
			"rut": "22222222-2"
		}
	},
	{
		"id": 64,
		"vehiculo": {
			"tipo": "Camion",
			"numeroMotor": 9213,
			"numeroRuedas": 17,
			"tipoCombustible": "Electrico",
			"maxLitros": 233,
			"marca": "MAN",
			"precio": 105000000,
			"anio": 1999,
			"numeroPuertas": 2
		},
		"cliente": {
			"nombre": "Juan",
			"rut": "11111111-1"
		}
	},
	{
		"id": 65,
		"vehiculo": {
			"tipo": "Camion",
			"numeroMotor": 7658,
			"numeroRuedas": 7,
			"tipoCombustible": "Gas",
			"maxLitros": 473,
			"marca": "MAN",
			"precio": 105000000,
			"anio": 1982,
			"numeroPuertas": 3
		},
		"cliente": {
			"nombre": "Sofia",
			"rut": "66666666-6"
		}
	},
	{
		"id": 66,
		"vehiculo": {
			"tipo": "Auto",
			"numeroMotor": 5512,
			"numeroRuedas": 4,
			"tipoCombustible": "Gasolina",
			"maxLitros": 61,
			"marca": "Chevrolet",
			"precio": 18000000,
			"anio": 2023,
			"numeroPuertas": 3
		},
		"cliente": {
			"nombre": "Pedro",
			"rut": "22222222-2"
		}
	},
	{
		"id": 67,
		"vehiculo": {
			"tipo": "Auto",
			"numeroMotor": 4515,
			"numeroRuedas": 4,
			"tipoCombustible": "Gasolina",
			"maxLitros": 67,
			"marca": "Suzuki",
			"precio": 12000000,
			"anio": 2007,
			"numeroPuertas": 5
		},
		"cliente": {
			"nombre": "Ana",
			"rut": "44444444-4"
		}
	},
	{
		"id": 68,
		"vehiculo": {
			"tipo": "Auto",
			"numeroMotor": 4329,
			"numeroRuedas": 4,
			"tipoCombustible": "Gasolina",
			"maxLitros": 55,
			"marca": "Chevrolet",
			"precio": 18000000,
			"anio": 2015,
			"numeroPuertas": 2
		},
		"cliente": {
			"nombre": "Sofia",
			"rut": "66666666-6"
		}
	},
	{
		"id": 69,
		"vehiculo": {
			"tipo": "Moto",
			"numeroMotor": 7803,
			"numeroRuedas": 2,
			"tipoCombustible": "Gas",
			"maxLitros": 22,
			"marca": "KTM",
			"precio": 5000000,
			"anio": 1986
		},
		"cliente": {
			"nombre": "Luis",
			"rut": "77777777-7"
		}
	},
	{
		"id": 70,
		"vehiculo": {
			"tipo": "Moto",
			"numeroMotor": 6477,
			"numeroRuedas": 2,
			"tipoCombustible": "Gasolina",
			"maxLitros": 26,
			"marca": "Kawasaki",
			"precio": 13000000,
			"anio": 1989
		},
		"cliente": {
			"nombre": "Carlos",
			"rut": "55555555-5"
		}
	},
	{
		"id": 71,
		"vehiculo": {
			"tipo": "Auto",
			"numeroMotor": 6717,
			"numeroRuedas": 4,
			"tipoCombustible": "Gas",
			"maxLitros": 60,
			"marca": "Ford",
			"precio": 17000000,
			"anio": 1986,
			"numeroPuertas": 3
		},
		"cliente": {
			"nombre": "Luis",
			"rut": "77777777-7"
		}
	},
	{
		"id": 72,
		"vehiculo": {
			"tipo": "Auto",
			"numeroMotor": 6283,
			"numeroRuedas": 4,
			"tipoCombustible": "Electrico",
			"maxLitros": 59,
			"marca": "Toyota",
			"precio": 19000000,
			"anio": 1985,
			"numeroPuertas": 3
		},
		"cliente": {
			"nombre": "Carlos",
			"rut": "55555555-5"
		}
	},
	{
		"id": 73,
		"vehiculo": {
			"tipo": "Camion",
			"numeroMotor": 7959,
			"numeroRuedas": 14,
			"tipoCombustible": "Gas",
			"maxLitros": 263,
			"marca": "Isuzu",
			"precio": 70000000,
			"anio": 1997,
			"numeroPuertas": 3
		},
		"cliente": {
			"nombre": "Sofia",
			"rut": "66666666-6"
		}
	},
	{
		"id": 74,
		"vehiculo": {
			"tipo": "Moto",
			"numeroMotor": 7335,
			"numeroRuedas": 2,
			"tipoCombustible": "Gasolina",
			"maxLitros": 17,
			"marca": "Suzuki",
			"precio": 8000000,
			"anio": 2016
		},
		"cliente": {
			"nombre": "Ana",
			"rut": "44444444-4"
		}
	},
	{
		"id": 75,
		"vehiculo": {
			"tipo": "Camion",
			"numeroMotor": 1911,
			"numeroRuedas": 5,
			"tipoCombustible": "Electrico",
			"maxLitros": 351,
			"marca": "MAN",
			"precio": 105000000,
			"anio": 1998,
			"numeroPuertas": 2
		},
		"cliente": {
			"nombre": "Maria",
			"rut": "33333333-3"
		}
	},
	{
		"id": 76,
		"vehiculo": {
			"tipo": "Moto",
			"numeroMotor": 7178,
			"numeroRuedas": 2,
			"tipoCombustible": "Electrico",
			"maxLitros": 17,
			"marca": "Honda",
			"precio": 15000000,
			"anio": 2009
		},
		"cliente": {
			"nombre": "Pedro",
			"rut": "22222222-2"
		}
	},
	{
		"id": 77,
		"vehiculo": {
			"tipo": "Moto",
			"numeroMotor": 9692,
			"numeroRuedas": 2,
			"tipoCombustible": "Electrico",
			"maxLitros": 10,
			"marca": "KTM",
			"precio": 5000000,
			"anio": 2010
		},
		"cliente": {
			"nombre": "Maria",
			"rut": "33333333-3"
		}
	},
	{
		"id": 78,
		"vehiculo": {
			"tipo": "Moto",
			"numeroMotor": 4589,
			"numeroRuedas": 2,
			"tipoCombustible": "Gas",
			"maxLitros": 21,
			"marca": "Honda",
			"precio": 15000000,
			"anio": 1980
		},
		"cliente": {
			"nombre": "Ana",
			"rut": "44444444-4"
		}
	},
	{
		"id": 79,
		"vehiculo": {
			"tipo": "Camion",
			"numeroMotor": 7612,
			"numeroRuedas": 16,
			"tipoCombustible": "Gasolina",
			"maxLitros": 456,
			"marca": "Iveco",
			"precio": 85000000,
			"anio": 1989,
			"numeroPuertas": 2
		},
		"cliente": {
			"nombre": "Pedro",
			"rut": "22222222-2"
		}
	},
	{
		"id": 80,
		"vehiculo": {
			"tipo": "Auto",
			"numeroMotor": 8824,
			"numeroRuedas": 4,
			"tipoCombustible": "Gasolina",
			"maxLitros": 57,
			"marca": "Toyota",
			"precio": 19000000,
			"anio": 2019,
			"numeroPuertas": 2
		},
		"cliente": {
			"nombre": "Juan",
			"rut": "11111111-1"
		}
	},
	{
		"id": 81,
		"vehiculo": {
			"tipo": "Auto",
			"numeroMotor": 4374,
			"numeroRuedas": 4,
			"tipoCombustible": "Gasolina",
			"maxLitros": 62,
			"marca": "Suzuki",
			"precio": 12000000,
			"anio": 1993,
			"numeroPuertas": 3
		},
		"cliente": {
			"nombre": "Luis",
			"rut": "77777777-7"
		}
	},
	{
		"id": 82,
		"vehiculo": {
			"tipo": "Camion",
			"numeroMotor": 1784,
			"numeroRuedas": 6,
			"tipoCombustible": "Gas",
			"maxLitros": 274,
			"marca": "Mercedes",
			"precio": 110000000,
			"anio": 2010,
			"numeroPuertas": 3
		},
		"cliente": {
			"nombre": "Pedro",
			"rut": "22222222-2"
		}
	},
	{
		"id": 83,
		"vehiculo": {
			"tipo": "Moto",
			"numeroMotor": 4419,
			"numeroRuedas": 2,
			"tipoCombustible": "Gasolina",
			"maxLitros": 24,
			"marca": "Yamaha",
			"precio": 14000000,
			"anio": 2003
		},
		"cliente": {
			"nombre": "Sofia",
			"rut": "66666666-6"
		}
	},
	{
		"id": 84,
		"vehiculo": {
			"tipo": "Auto",
			"numeroMotor": 8787,
			"numeroRuedas": 4,
			"tipoCombustible": "Gasolina",
			"maxLitros": 65,
			"marca": "Honda",
			"precio": 21000000,
			"anio": 2023,
			"numeroPuertas": 4
		},
		"cliente": {
			"nombre": "Maria",
			"rut": "33333333-3"
		}
	},
	{
		"id": 85,
		"vehiculo": {
			"tipo": "Camion",
			"numeroMotor": 7285,
			"numeroRuedas": 4,
			"tipoCombustible": "Gas",
			"maxLitros": 429,
			"marca": "Iveco",
			"precio": 85000000,
			"anio": 1991,
			"numeroPuertas": 3
		},
		"cliente": {
			"nombre": "Luis",
			"rut": "77777777-7"
		}
	},
	{
		"id": 86,
		"vehiculo": {
			"tipo": "Camion",
			"numeroMotor": 1698,
			"numeroRuedas": 8,
			"tipoCombustible": "Gas",
			"maxLitros": 407,
			"marca": "Scania",
			"precio": 95000000,
			"anio": 2023,
			"numeroPuertas": 2
		},
		"cliente": {
			"nombre": "Sofia",
			"rut": "66666666-6"
		}
	},
	{
		"id": 87,
		"vehiculo": {
			"tipo": "Moto",
			"numeroMotor": 8206,
			"numeroRuedas": 2,
			"tipoCombustible": "Electrico",
			"maxLitros": 14,
			"marca": "Yamaha",
			"precio": 14000000,
			"anio": 2013
		},
		"cliente": {
			"nombre": "Ana",
			"rut": "44444444-4"
		}
	},
	{
		"id": 88,
		"vehiculo": {
			"tipo": "Auto",
			"numeroMotor": 2258,
			"numeroRuedas": 4,
			"tipoCombustible": "Electrico",
			"maxLitros": 59,
			"marca": "Toyota",
			"precio": 19000000,
			"anio": 2022,
			"numeroPuertas": 2
		},
		"cliente": {
			"nombre": "Luis",
			"rut": "77777777-7"
		}
	},
	{
		"id": 89,
		"vehiculo": {
			"tipo": "Auto",
			"numeroMotor": 6718,
			"numeroRuedas": 4,
			"tipoCombustible": "Gas",
			"maxLitros": 47,
			"marca": "Chevrolet",
			"precio": 18000000,
			"anio": 1992,
			"numeroPuertas": 4
		},
		"cliente": {
			"nombre": "Carlos",
			"rut": "55555555-5"
		}
	},
	{
		"id": 90,
		"vehiculo": {
			"tipo": "Camion",
			"numeroMotor": 7928,
			"numeroRuedas": 4,
			"tipoCombustible": "Electrico",
			"maxLitros": 458,
			"marca": "MAN",
			"precio": 105000000,
			"anio": 1988,
			"numeroPuertas": 2
		},
		"cliente": {
			"nombre": "Juan",
			"rut": "11111111-1"
		}
	},
	{
		"id": 91,
		"vehiculo": {
			"tipo": "Moto",
			"numeroMotor": 6424,
			"numeroRuedas": 2,
			"tipoCombustible": "Gas",
			"maxLitros": 29,
			"marca": "Suzuki",
			"precio": 8000000,
			"anio": 2001
		},
		"cliente": {
			"nombre": "Sofia",
			"rut": "66666666-6"
		}
	},
	{
		"id": 92,
		"vehiculo": {
			"tipo": "Moto",
			"numeroMotor": 1412,
			"numeroRuedas": 2,
			"tipoCombustible": "Gasolina",
			"maxLitros": 27,
			"marca": "BMW",
			"precio": 18000000,
			"anio": 2012
		},
		"cliente": {
			"nombre": "Pedro",
			"rut": "22222222-2"
		}
	},
	{
		"id": 93,
		"vehiculo": {
			"tipo": "Moto",
			"numeroMotor": 4262,
			"numeroRuedas": 2,
			"tipoCombustible": "Gas",
			"maxLitros": 23,
			"marca": "Honda",
			"precio": 15000000,
			"anio": 2023
		},
		"cliente": {
			"nombre": "Sofia",
			"rut": "66666666-6"
		}
	},
	{
		"id": 94,
		"vehiculo": {
			"tipo": "Camion",
			"numeroMotor": 6139,
			"numeroRuedas": 14,
			"tipoCombustible": "Gasolina",
			"maxLitros": 475,
			"marca": "Mercedes",
			"precio": 110000000,
			"anio": 1980,
			"numeroPuertas": 2
		},
		"cliente": {
			"nombre": "Pedro",
			"rut": "22222222-2"
		}
	},
	{
		"id": 95,
		"vehiculo": {
			"tipo": "Camion",
			"numeroMotor": 8751,
			"numeroRuedas": 14,
			"tipoCombustible": "Gasolina",
			"maxLitros": 407,
			"marca": "Scania",
			"precio": 95000000,
			"anio": 1987,
			"numeroPuertas": 3
		},
		"cliente": {
			"nombre": "Pedro",
			"rut": "22222222-2"
		}
	},
	{
		"id": 96,
		"vehiculo": {
			"tipo": "Moto",
			"numeroMotor": 5185,
			"numeroRuedas": 2,
			"tipoCombustible": "Gasolina",
			"maxLitros": 13,
			"marca": "Yamaha",
			"precio": 14000000,
			"anio": 1995
		},
		"cliente": {
			"nombre": "Juan",
			"rut": "11111111-1"
		}
	},
	{
		"id": 97,
		"vehiculo": {
			"tipo": "Camion",
			"numeroMotor": 8347,
			"numeroRuedas": 16,
			"tipoCombustible": "Electrico",
			"maxLitros": 281,
			"marca": "Volvo",
			"precio": 100000000,
			"anio": 2017,
			"numeroPuertas": 2
		},
		"cliente": {
			"nombre": "Maria",
			"rut": "33333333-3"
		}
	},
	{
		"id": 98,
		"vehiculo": {
			"tipo": "Camion",
			"numeroMotor": 9660,
			"numeroRuedas": 8,
			"tipoCombustible": "Electrico",
			"maxLitros": 367,
			"marca": "Mercedes",
			"precio": 110000000,
			"anio": 2009,
			"numeroPuertas": 3
		},
		"cliente": {
			"nombre": "Juan",
			"rut": "11111111-1"
		}
	},
	{
		"id": 99,
		"vehiculo": {
			"tipo": "Moto",
			"numeroMotor": 6641,
			"numeroRuedas": 2,
			"tipoCombustible": "Gasolina",
			"maxLitros": 13,
			"marca": "KTM",
			"precio": 5000000,
			"anio": 1997
		},
		"cliente": {
			"nombre": "Carlos",
			"rut": "55555555-5"
		}
	},
	{
		"id": 100,
		"vehiculo": {
			"tipo": "Camion",
			"numeroMotor": 4303,
			"numeroRuedas": 4,
			"tipoCombustible": "Electrico",
			"maxLitros": 289,
			"marca": "Isuzu",
			"precio": 70000000,
			"anio": 1985,
			"numeroPuertas": 3
		},
		"cliente": {
			"nombre": "Pedro",
			"rut": "22222222-2"
		}
	}
]